{
  "_class": "bitmap",
  "booleanOperation": -1,
  "clippingMask": "{{0, 0}, {1, 1}}",
  "clippingMaskMode": 0,
  "do_objectID": "2F222498-AE12-4881-8061-EF7E2B8460C5",
  "exportOptions": {
    "_class": "exportOptions",
    "do_objectID": "C8EEEE34-8240-4A7F-A110-A9B0059329AE",
    "exportFormats": [
    ],
    "includedLayerIds": [
    ],
    "layerOptions": 0,
    "shouldTrim": false
  },
  "fillReplacesImage": false,
  "frame": {
    "_class": "rect",
    "constrainProportions": true,
    "do_objectID": "557A9466-F591-4056-AA7B-F8E8D4568939",
    "height": 513,
    "width": 1237,
    "x": 884,
    "y": -2843
  },
  "hasClippingMask": false,
  "image": {
    "_class": "MSJSONFileReference",
    "_ref": "images/1debf96c0d6904191dbb163e85ace31ede176ab4.png",
    "_ref_class": "MSImageData"
  },
  "intendedDPI": 144,
  "isFixedToViewport": false,
  "isFlippedHorizontal": false,
  "isFlippedVertical": false,
  "isLocked": false,
  "isVisible": true,
  "layerListExpandedType": 0,
  "name": "Bitmap",
  "nameIsFixed": false,
  "resizingConstraint": 63,
  "resizingType": 0,
  "rotation": 0,
  "shouldBreakMaskChain": false,
  "style": {
    "_class": "style",
    "do_objectID": "A8AB32CC-9FD6-47BB-A1FE-E164B736AC4B",
    "endMarkerType": 0,
    "miterLimit": 10,
    "startMarkerType": 0,
    "windingRule": 1
  }
}