{
  "_class": "shapeGroup",
  "booleanOperation": 0,
  "clippingMaskMode": 0,
  "do_objectID": "9FC06FD5-D5B2-4BDA-8910-91918CB7DB74",
  "exportOptions": {
    "_class": "exportOptions",
    "do_objectID": "05890C0B-5738-4029-B3A7-62F7D8EA4AD6",
    "exportFormats": [
    ],
    "includedLayerIds": [
    ],
    "layerOptions": 0,
    "shouldTrim": false
  },
  "frame": {
    "_class": "rect",
    "constrainProportions": false,
    "do_objectID": "BCA7ADB4-2461-4454-A35D-66C1C152CC1E",
    "height": 16.20896178409917,
    "width": 16.28514961857223,
    "x": -5.521667423705367,
    "y": 2.305900177741933
  },
  "groupLayout": {
    "_class": "MSImmutableFreeformGroupLayout"
  },
  "hasClickThrough": false,
  "hasClippingMask": false,
  "isFixedToViewport": false,
  "isFlippedHorizontal": false,
  "isFlippedVertical": false,
  "isLocked": false,
  "isVisible": true,
  "layerListExpandedType": 1,
  "layers": [
    {
      "class": "shapePath",
      "id": "0D6E6EAD-FA95-4571-84D4-F8024DC46AE7"
    }
  ],
  "name": "Line 20",
  "nameIsFixed": false,
  "resizingConstraint": 63,
  "resizingType": 0,
  "rotation": -45,
  "shouldBreakMaskChain": false,
  "style": {
    "_class": "style",
    "do_objectID": "C057E9A2-8993-49DE-89E3-677580E7778A",
    "endMarkerType": 0,
    "fills": [
      {
        "_class": "fill",
        "color": {
          "_class": "color",
          "alpha": 1,
          "blue": 0.592,
          "green": 0.592,
          "red": 0.592
        },
        "fillType": 0,
        "isEnabled": true,
        "noiseIndex": 0,
        "noiseIntensity": 0,
        "patternFillType": 1,
        "patternTileScale": 1
      }
    ],
    "miterLimit": 10,
    "startMarkerType": 0,
    "windingRule": 0
  },
  "windingRule": 0
}